<?xml version='1.0' encoding='UTF-8'?>
<archivalDocument xmlns="http://www.faustedition.net/ns" xmlns:tei="http://www.tei-c.org/ns/1.0" xmlns:f="http://www.faustedition.net/ns" xmlns:xsi="http://www.w3.org/2001/XMLSchema-instance" xsi:schemaLocation="http://www.faustedition.net/ns https://faustedition.uni-wuerzburg.de/xml/schema/metadata.xsd" xml:base="faust://xml/transcript/gsa/390789/">
   <revisionDesc>
      <change when="2012-11-08" who="bruening">encoded</change>
      <change when="2013-04-28" who="bruening">Nachweise</change>
      <change when="2013-12-19" who="henzel">leere Seite nachgetragen nach Ritschels
         Vorgaben</change>
      <change when="2014-10-08" who="pravida">headnote</change>
      <change when="2015-06-17" who="koehler">minimal headnote</change>
   </revisionDesc>
   <metadata>
      <headNote>Doppelblatt. – Zu ‚Faust I‘.</headNote>
      <note>Doppelblatt, 3 beschriebene Seiten. – Seite 1: Titelaufschrift (eigenhändig, Tinte).
         Seite 2–3: Reinschrift von Zusatzversen zu der Szene ‚Studierzimmer (2)‘ zu einem
         Weimarischen Inszenierungsversuchen zu ‚Faust I‘ (eigenhändig, Tinte).</note>
      <repository>gsa</repository>
      <idno type="faustedition">T 2 H</idno>
      <idno type="gsa_1">GSA 25/XVII,1,10:1</idno>
      <idno type="gsa_2">GSA 25/W 1368</idno>
      <idno type="gsa_ident">390789</idno>
      <idno type="wa_faust">none<!-- T 2 H --></idno>
      <textTranscript uri="390789.xml"/>
      <classification>Mundum</classification>
      <numberingList>
         <numbering name="Bleistiftfoliierung">Wohl eigenhändige Foliierung mit
            Bleistift</numbering>
      </numberingList>
      <dimensions>
         <width unit="mm">195</width>
         <height unit="mm">326</height>
      </dimensions>
      <format>2</format>
      <edges>cut</edges>
      <paperType>Konzeptpapier</paperType>
      <paperColour>gelblich</paperColour>
      <watermarkID>Gekroentes_Rautenkranzwappen_in_Bogenmitte</watermarkID>
      <references>
         <reference type="description" uri="faust://bibliography/wa_I_14">S. 317</reference>
         <reference type="description" uri="faust://bibliography/bohnenkamp1994">S. 260</reference>
         <reference type="text" uri="faust://bibliography/loeper1870">Tl. 1, S. 163</reference>
         <reference type="text" uri="faust://bibliography/wa_I_14">S. 317f.</reference>
         <reference type="text" uri="faust://bibliography/bohnenkamp1994">S. 260f.</reference>
         <reference type="text" uri="faust://bibliography/schoene2005">Bd. 1, S. 590</reference>
         <reference type="essay" uri="faust://bibliography/schillemeit1988">S. 656</reference>
         <reference type="essay" uri="faust://bibliography/bohnenkamp1994">S. 261</reference>
      </references>
   </metadata>
   <sheet>
      <leaf>
         <page>
            <metadata>
               <docTranscript uri="0002.xml"/>
            </metadata>
         </page>
         <page>
            <metadata>
               <docTranscript uri="0003.xml"/>
            </metadata>
         </page>
      </leaf>
      <leaf>
         <page>
            <metadata>
               <docTranscript uri="0004.xml"/>
            </metadata>
         </page>
         <page>
            <metadata>
               <docTranscript/>
               <!-- leer -->
            </metadata>
         </page>
      </leaf>
   </sheet>
   <f:metadataImport xmlns:ge="http://www.tei-c.org/ns/geneticEditions" xmlns:svg="http://www.w3.org/2000/svg">
      <f:archiveDatabase xml:space="preserve">
      <f:bemerkung>zur Datierung vgl. Bohnenkamp, S. 261</f:bemerkung>
      <f:bestandbildner>Goethe, Johann Wolfgang von / Werke</f:bestandbildner>
      <f:bestandnr>25</f:bestandnr>
      <f:blatt>2</f:blatt>
      <f:datierung>1814 oder 1819 (?)</f:datierung>
      <f:druckort>WA I 14, 314-321</f:druckort>
      <f:ident>390789</f:ident>
      <f:kurztitel>Weimarische Inscenirungsversuche. Zum Radziwillschen Faust. Monodrama.
So mag es bey der Fratze ...
WA: oS; vgl. I 14,317-318
Reinschrift
Zwei Geisterchöre für die Paktszene
Titel der Handschrift: "Zu Faust"</f:kurztitel>
      <f:ordnungsgruppe>Werke</f:ordnungsgruppe>
      <f:schrift>egh</f:schrift>
      <f:signatur>XVII,1,10:1</f:signatur>
      <f:zwueber>Dramatische Werke</f:zwueber>
    </f:archiveDatabase>
      <f:abrDissertation>
         <metadaten xmlns="">
            <p>GSA XVII (1,10) (WA I,14,319f.)</p>
            <p>Reinschrift</p>
            <p>Erstdruck: Compositionen zu Göthe's Faust. Berlin 1835, S. 173-183</p>
            <p> x , gelblichgrünlicher Bogen, Velinpapier, auf Quartheftformat gefaltet; ohne
               WZ;</p>
            <p>Seiten 13: Riemer br. Tinte in lat. Schrift Szene im Gartenhäuschen</p>
         </metadaten>
         <kommentar xmlns="">
            <p> Erweiterung der Szene `Ein Gartenhäuschen' (V. 3205-3216) zu einer "typische[n]
               Opernszene" mit "sich verschlingenden Solo- und Duettpartien" (Schillemeit,
               Radziwill, S. 646) sowie abschließendem Quartett. Zusammen mit der Szene `Zwey
               Teufelchen' (hier S. 250-253) im April 1814 zur Vertonung dem Fürsten Radziwill
               übersandt. Goethes Begleitbrief vom 11. 4. 1814: "Ich wünsche, daß die Scene des
               Garten- häuschens, in ihrer gegenwärtigen Form, der Musik mehr geeignet seyn möge,
               als sie es bisher in ihrem Laconismus gewesen." (WA IV,24,220) </p>
            <p>Z. 19f.: Der _ sonst nur geringfügig von der Handschrift abweichende _ Erstdruck hat
               hier: "Ich will kein' Ander. Was ich/ will? Nur dich, ich will nur dich."</p>
            <p>Z. 49 benommen] im Sinne von weggenommen, geraubt (vgl. DWB 1,1468f.). </p>
            <p>Zusatztexte für die Bühne</p>
            <p>
               <b>Zwei Geisterchöre für die Paktszene</b>
            </p>
         </kommentar>
         <metadaten xmlns="">
            <p>GSA XVII (1,10) (WAI,14,317)</p>
            <p>Reinschrift</p>
            <p>Erstdruck: Compositionen zu Göthe's Faust. Berlin 1835, S. 98-103 u. S. 104-110</p>
            <p>326 x 195 mm, grünliches Folioblatt, gerippt, als Quartheft gefaltet; angeschnittenes
               WZ: Rautenkranzoval über Stern (Remdaer Wappenpapier);</p>
            <p>Seite 1: G schw.br. Tinte: "Zu Faust";</p>
            <p>Seiten 2 und 3: G schw.br. Tinte Chöre zur Paktszene;</p>
            <p>Seite 4: leer</p>
         </metadaten>
         <kommentar xmlns="">
            <p>
               <img src="./KL_U2_02.JPG" width="82" height="10" align="middle"/> Diese für die
               Vertonung des Füsten Radziwill geschriebenen Geisterchöre sollten während und nach
               dem Paktschluß (zwischen V. 1739 und 1740 sowie nach 2072) eingefügt werden, wie die
               von Goethe notierten Anschlußverse aus dem `Faust'-Text zeigen. Sie wurden
               wahrscheinlich erstmalig am 4. Juli 1819 nach Berlin gesandt. Vgl. Tagebuch WA
               III,7,66 und Goethes Begleitbrief an P. A. Wolff: "[...] sende das Verlangte, mit der
               Bitte mich meinen hohen Gönnern und Freunden bestens zu empfehlen; zugleich mit
               Versicherung daß ich jederzeit bereit bin jenen löblichen, mir so ehrenvollen Zweck
               nach Kräften zu befördern. Schreiben Sie mir nur immer gefälligst was man wünscht."
               (WA IV,31,209) Ob diese Chöre wie die übrigen Zusätze für Radziwill schon 1814 oder
               auf neuerliche Nachfrage erst 1819 entstanden, ist nicht bekannt. Radziwills
               Komposition sieht für den ersten Chor "2 Tenöre/ 2 Baßstimmen", für den zweiten
               "Sopran/Alt/Tenor/Baß" vor. Am 21. Mai 1820 berichtet Zelter nach Weimar: "Zuerst
               also von gestern, das ist: von der ersten Probe des `Faust', von der ich nicht viel
               mehr zu sagen weiss, als dass die heutige besser ausfallen wird. Die neuen Chöre:
               `Wird er schreiben'? und der Abfahrtschor gingen, trotz des spillerigen Stils, zum
               erstenmale nicht schlecht." (Zelter-Briefwechsel, Bd. II, S. 75.) </p>
            <p>Zusatztexte für die Bühne</p>
            <p>
               <b>Faust als Monodrama (1815)</b>
            </p>
         </kommentar>
      </f:abrDissertation>
      <f:inventoryDatabase>
         <f:field>
            <f:key n="06">Beschreibung (für Anzeige vor Überlieferungsform)</f:key>
            <f:value>Zwei Geisterchöre für die Paktszene</f:value>
         </f:field>
         <f:field>
            <f:key n="08">Signatur</f:key>
            <f:value>25/XVII,1,10:1</f:value>
         </f:field>
         <f:field>
            <f:key n="081">Bestandsbezeichnung</f:key>
            <f:value>Bestand Goethe, Johann Wolfgang von / Werke</f:value>
         </f:field>
         <f:field>
            <f:key n="11">Kurzbezeichnung (WA-Kategorie mit Texterstreckung)</f:key>
            <f:value>Weimarische Inscenirungsversuche. Zum Radziwillschen Faust. Monodrama. WA I 14,
               314-321</f:value>
         </f:field>
         <f:field>
            <f:key n="11z">Druckstelle in der WA</f:key>
            <f:value>I 14,314</f:value>
         </f:field>
         <f:field>
            <f:key n="12a">Zitiertitel der Handschrift</f:key>
            <f:value>"Zu Faust"</f:value>
         </f:field>
         <f:field>
            <f:key n="12e">ermittelte Datierung</f:key>
            <f:value>1814 oder 1819 (?)</f:value>
         </f:field>
         <f:field>
            <f:key n="12i">Index-Datum</f:key>
            <f:value>1814?</f:value>
         </f:field>
         <f:field>
            <f:key n="14">vorgefundenes Inzipit</f:key>
            <f:value>So mag es bey der Fratze</f:value>
         </f:field>
         <f:field>
            <f:key n="20">Handschriftennachweis in WA und SNA</f:key>
            <f:value>I 14,317-318</f:value>
         </f:field>
         <f:field>
            <f:key n="25">Sigle</f:key>
            <f:value>oS</f:value>
         </f:field>
         <f:field>
            <f:key n="30">Schrift</f:key>
            <f:value>egh</f:value>
         </f:field>
         <f:field>
            <f:key n="333">Überlieferungsform</f:key>
            <f:value>Reinschrift</f:value>
         </f:field>
         <f:field>
            <f:key n="80">Blattzahl</f:key>
            <f:value>2</f:value>
         </f:field>
         <f:field>
            <f:key n="91">Kommentar</f:key>
            <f:value>zur Datierung vgl. Bohnenkamp, S. 261</f:value>
         </f:field>
         <f:field>
            <f:key n="994">Filmnummer</f:key>
            <f:value>1044</f:value>
         </f:field>
         <f:field>
            <f:key n="xx0">Datensatznr.</f:key>
            <f:value>4123</f:value>
         </f:field>
      </f:inventoryDatabase>
   </f:metadataImport>
</archivalDocument>