<?xml version='1.0' encoding='UTF-8'?>
<archivalDocument xmlns="http://www.faustedition.net/ns" xmlns:tei="http://www.tei-c.org/ns/1.0" xmlns:f="http://www.faustedition.net/ns" xmlns:xsi="http://www.w3.org/2001/XMLSchema-instance" xsi:schemaLocation="http://www.faustedition.net/ns https://faustedition.uni-wuerzburg.de/xml/schema/metadata.xsd" xml:base="faust://xml/transcript/gsa/391405/">
   <revisionDesc>
      <change when="2012-11-19" who="bruening">encoded</change>
      <change when="2014-11-11" who="pravida">headnote</change>
      <change when="2015-02-04" who="koehler">minimal headnote</change>
      <change when="2015-06-18" who="koehler">minimal headnote</change>
   </revisionDesc>
   <metadata>
      <headNote>Doppelblatt. – Zu ‚Faust II‘, Akt. 1.</headNote>
      <note>dabei eigenhändige Notizen Goethes: „Gersdorf 3 Fr v Germ 1“
         Doppelblatt, 3 beschriebene Seiten. – S. 1: Versentwürfe zu ‚Faust II‘, Akt. 1
         (eigenhändig, Bleistift). S. 2: unbeschrieben. S. 3: Stichworte (eigenhändig, Bleistift).
         S. 4: Versentwürfe zu ‚Faust II‘, Akt. 1 (eigenhändig, Bleistift).</note>
      <repository>gsa</repository>
      <idno type="faustedition">2 I H.46</idno>
      <idno type="gsa_1">GSA 25/XVII,5,17</idno>
      <idno type="gsa_2">GSA 25/W 1469</idno>
      <idno type="gsa_ident">391405</idno>
      <idno type="wa_faust">2 I H.46</idno>
      <textTranscript uri="391405.xml"/>
      <classification>Konzept</classification>
      <condition>Stockfleckig, an den Rändern vergilbt.</condition>
      <format>4</format>
      <edges>uncut</edges>
      <paperType>Briefpapier</paperType>
      <paperColour>gelblich</paperColour>
      <watermarkID>GM</watermarkID>
      <references>
         <reference type="description" uri="faust://bibliography/wa_I_15_2">S. 12</reference>
         <reference type="description" uri="faust://bibliography/bohnenkamp1994">S. 374</reference>
         <reference type="text" uri="faust://bibliography/bohnenkamp1994">S. 374f.</reference>
         <reference type="text" uri="faust://bibliography/schoene2005">Bd. 1, S. 619</reference>
         <reference type="essay" uri="faust://bibliography/bohnenkamp1994">S. 376</reference>
      </references>
   </metadata>
   <sheet>
      <leaf>
         <metadata>
            <dimensions>
               <width unit="mm">210</width>
               <height unit="mm">245</height>
            </dimensions>
            <note>Der Mindestwert für die Blatt-Breite ist 204, der für die Höhe 240 mm.</note>
         </metadata>
         <page>
            <metadata>
               <docTranscript uri="0002.xml"/>
            </metadata>
         </page>
         <page>
            <metadata>
               <docTranscript/>
               <!-- leer -->
            </metadata>
         </page>
      </leaf>
      <leaf>
         <metadata>
            <dimensions>
               <width unit="mm">200</width>
               <height unit="mm">250</height>
            </dimensions>
            <note>Der Mindestwert für die Blatt-Breite ist 195, der für die Blatthöhe 245 mm.</note>
         </metadata>
         <page>
            <metadata>
               <docTranscript uri="0006.xml"/>
            </metadata>
         </page>
         <page>
            <metadata>
               <docTranscript uri="0004.xml"/>
            </metadata>
         </page>
      </leaf>
   </sheet>
   <f:metadataImport xmlns:ge="http://www.tei-c.org/ns/geneticEditions" xmlns:svg="http://www.w3.org/2000/svg">
      <f:archiveDatabase xml:space="preserve">
      <f:bemerkung>zur Datierung vgl. Bohnenkamp, S.376</f:bemerkung>
      <f:bestandbildner>Goethe, Johann Wolfgang von / Werke</f:bestandbildner>
      <f:bestandnr>25</f:bestandnr>
      <f:blatt>2</f:blatt>
      <f:dabei_vermerk>Notizen egh: "Gersdorf 3" [Gersdorff, Ernst Christian August (?)], "Fr v Germ 1"</f:dabei_vermerk>
      <f:datierung>1828/1829 (?)</f:datierung>
      <f:druckort>WA I 15.1, 8-89</f:druckort>
      <f:ident>391405</f:ident>
      <f:kurztitel>Faust. Zweiter Theil. Erster Act. Kaiserliche Pfalz
WA: I H.46; vgl. I 15.2,12

Vers(e): 6057-6080
Zu wissen sey es jedem ...
Konzept

Vers(e): 6099-6106 (6101-60102 fehlt/fehlen)
Ein schönes Kind ...
Konzept</f:kurztitel>
      <f:ordnungsgruppe>Werke</f:ordnungsgruppe>
      <f:schrift>egh</f:schrift>
      <f:signatur>XVII,5,17</f:signatur>
      <f:zwueber>Dramatische Werke</f:zwueber>
    </f:archiveDatabase>
      <f:abrDissertation>
         <metadaten xmlns="">
            <!-- FIX: Schreibfehler im Originaltext - "GSA XIII" zu "GSA XVII" -->
            <p>GSA XVII (5,17) (WA I,15.2,12 u. 31f.)</p>
            <p>Entwurf</p>
            <p>Erstdruck: WA I,15.2,31f. (teilweise)</p>
            <p> x , hellgelbliches Papier, großer Foliobogen, gefaltet, gerippt, rechts Rißkante, an
               den Rändern sehr abgestoßen, fleckig; WZ: `C M';</p>
            <p>Seite 1: G Blei 60576068 Var, 6072f. Var;</p>
            <p>Seite 2: leer;</p>
            <p>Seite 3: G Blei Stichworte: "Gersdorf 3 / Frl Germ 1";</p>
            <p>Seite 4: G Blei 6099f. Var, 6079f. Var, 61036106ff. Var, 60736078 Var</p>
         </metadaten>
         <kommentar xmlns="">
            <p>Dieses Entwurfsblatt zur Papiergeldszene bietet keine äußeren Anhaltspunkte für die
               Datierung; da das Motiv jedoch weder im Schema noch im Bereich der übrigen Skizzen
               schon auftaucht, handelt es sich offensichtlich um eine spätere Hinzufügung. Die
               Anhaltspunkte für die Entstehung der Szene `Lustgarten' sind spärlich; die
               datierbaren Handschriften (I H43, I H45, I Hm, vgl. hier S. 287, Anm. 43) betreffen
               nur den Teil der Szene, der bereits im Februar 1828 abgeschlossen vorlag und schon in
               Band 12 der `Ausgabe letzter Hand' gedruckt wurde (bis Vers 6036). Zu der darauf erst
               folgenden eigentlichen Papiergeldszene ist lediglich das hier dokumentierte Blatt I
               H46 überliefert; den einzigen Anhaltspunkt für den Entstehungszeitraum gibt der
               Bericht Eckermanns, der von dieser Szene am 27. 12. 1829 als abgeschlossen
               berichtet.</p>
            <p>Während ein großer Teil der Verse im vorliegenden Entwurf schon die gültige Fassung
               erreicht hat oder ihr nahekommt, ist die Anordnung der Verse noch vergleichsweise
               weit vom endgültigen Text entfernt. Einige Verse (Z. 19f. u. 30f.) dieses Entwurfs
               wurden schon von Strehlke (S. 66) unter die Paralipomena aufgenommen; in der BA
               wurden dann Z. 19-30 _ mit den stark abweichenden Lesungen aus den `Lesarten' der WA
               _ zu den `Skizzen und Varianten' gestellt (S. 659).</p>
            <p>Z. 16: Charakteristisch für Goethes Arbeitsweise. Er notiert sich zunächst nur das
               Reimwort des noch fehlenden Verses (V. 6071: Nacht) und läßt Raum, der nachträglich
               ausgefüllt werden soll.</p>
            <p>Z. 20 schmunzt] vermutlich thüringische Nebenform zu `schmunzelt' (DWB 15,1134).</p>
            <p>Z. 20 und blickt ein hold[er] Schedel] WA und BA verzeichnen hier Spatium.</p>
            <p>Z. 22-25: WA (und entsprechend BA) gibt hier irrtümlich V. 6079f.</p>
            <p>Z. 27f.: WA (und entsprechend BA) verzeichnet Lücke vor "schlagen" und "tragen".</p>
            <p>IH60</p>
            <p>
               <b>I H60</b>
            </p>
         </kommentar>
      </f:abrDissertation>
      <f:inventoryDatabase>
         <f:field>
            <f:key n="08">Signatur</f:key>
            <f:value>25/XVII,5,17</f:value>
         </f:field>
         <f:field>
            <f:key n="081">Bestandsbezeichnung</f:key>
            <f:value>Bestand Goethe, Johann Wolfgang von / Werke</f:value>
         </f:field>
         <f:field>
            <f:key n="12e">ermittelte Datierung</f:key>
            <f:value>1828/1829 (?)</f:value>
         </f:field>
         <f:field>
            <f:key n="20">Handschriftennachweis in WA und SNA</f:key>
            <f:value>I 15.2,12</f:value>
         </f:field>
         <f:field>
            <f:key n="25">Sigle</f:key>
            <f:value>I H.46</f:value>
         </f:field>
         <f:field>
            <f:key n="60">Agenda</f:key>
            <f:value>Original beschädigt</f:value>
         </f:field>
         <f:field>
            <f:key n="70">Personen</f:key>
            <f:value>Gersdorff, Ernst Christian August von</f:value>
         </f:field>
         <f:field>
            <f:key n="80">Blattzahl</f:key>
            <f:value>2</f:value>
         </f:field>
         <f:field>
            <f:key n="90">dabei-Vermerk</f:key>
            <f:value>Notizen egh: "Gersdorf 3" [Gersdorff, Ernst Christian August (?)], "Fr v Germ
               1"</f:value>
         </f:field>
         <f:field>
            <f:key n="91">Kommentar</f:key>
            <f:value>zur Datierung vgl. Bohnenkamp, S.376</f:value>
         </f:field>
         <f:field>
            <f:key n="994">Filmnummer</f:key>
            <f:value>1129</f:value>
         </f:field>
         <f:field>
            <f:key n="xx0">Datensatznr.</f:key>
            <f:value>3070</f:value>
         </f:field>
      </f:inventoryDatabase>
      <f:inventoryDatabase>
         <f:field>
            <f:key n="08">Signatur</f:key>
            <f:value>25/XVII,5,17*a</f:value>
         </f:field>
         <f:field>
            <f:key n="081">Bestandsbezeichnung</f:key>
            <f:value>Bestand Goethe, Johann Wolfgang von / Werke</f:value>
         </f:field>
         <f:field>
            <f:key n="11">Kurzbezeichnung (WA-Kategorie mit Texterstreckung)</f:key>
            <f:value>Faust II. WA I 15.1, 1-I 15.2, 247</f:value>
         </f:field>
         <f:field>
            <f:key n="11z">Druckstelle in der WA</f:key>
            <f:value>I 15.1,8</f:value>
         </f:field>
         <f:field>
            <f:key n="14">vorgefundenes Inzipit</f:key>
            <f:value>Zu wissen sey es jedem</f:value>
         </f:field>
         <f:field>
            <f:key n="30">Schrift</f:key>
            <f:value>egh</f:value>
         </f:field>
         <f:field>
            <f:key n="333">Überlieferungsform</f:key>
            <f:value>Konzept</f:value>
         </f:field>
         <f:field>
            <f:key n="41v">Verszahlen</f:key>
            <f:value>6057-6080</f:value>
         </f:field>
         <f:field>
            <f:key n="xx0">Datensatznr.</f:key>
            <f:value>3123</f:value>
         </f:field>
      </f:inventoryDatabase>
      <f:inventoryDatabase>
         <f:field>
            <f:key n="08">Signatur</f:key>
            <f:value>25/XVII,5,17*b</f:value>
         </f:field>
         <f:field>
            <f:key n="081">Bestandsbezeichnung</f:key>
            <f:value>Bestand Goethe, Johann Wolfgang von / Werke</f:value>
         </f:field>
         <f:field>
            <f:key n="11">Kurzbezeichnung (WA-Kategorie mit Texterstreckung)</f:key>
            <f:value>Faust II. WA I 15.1, 1-I 15.2, 247</f:value>
         </f:field>
         <f:field>
            <f:key n="11z">Druckstelle in der WA</f:key>
            <f:value>I 15.1,8</f:value>
         </f:field>
         <f:field>
            <f:key n="14">vorgefundenes Inzipit</f:key>
            <f:value>Ein schönes Kind</f:value>
         </f:field>
         <f:field>
            <f:key n="30">Schrift</f:key>
            <f:value>egh</f:value>
         </f:field>
         <f:field>
            <f:key n="333">Überlieferungsform</f:key>
            <f:value>Konzept</f:value>
         </f:field>
         <f:field>
            <f:key n="41f">fehlende Verse</f:key>
            <f:value>6101-60102</f:value>
         </f:field>
         <f:field>
            <f:key n="41v">Verszahlen</f:key>
            <f:value>6099-6106</f:value>
         </f:field>
         <f:field>
            <f:key n="xx0">Datensatznr.</f:key>
            <f:value>4052</f:value>
         </f:field>
      </f:inventoryDatabase>
   </f:metadataImport>
</archivalDocument>