<?xml version='1.0' encoding='UTF-8'?>
<archivalDocument xmlns="http://www.faustedition.net/ns" xmlns:tei="http://www.tei-c.org/ns/1.0" xmlns:f="http://www.faustedition.net/ns" xmlns:xsi="http://www.w3.org/2001/XMLSchema-instance" xsi:schemaLocation="http://www.faustedition.net/ns https://faustedition.uni-wuerzburg.de/xml/schema/metadata.xsd" xml:base="faust://xml/transcript/gsa/390884/">
   <revisionDesc>
      <change when="2012-11-28" who="bruening">encoded</change>
      <change when="2013-11-18" who="ritter">idno aktualisiert</change>
      <change when="2014-11-13" who="pravida">headnote</change>
      <change when="2015-02-04" who="koehler">minimal headnote</change>
      <change when="2015-06-18" who="koehler">minimal headnote</change>
   </revisionDesc>
   <metadata>
      <headNote>Zettel. – Zu ‚Faust II‘, Akt 2.</headNote>
      <note>Fragment aus dem Theaterzettel zur Aufführung von Webers „Freischütz“ auf dem Weimarer
         Theater am 29. September 1827 (faust://bibliography/wa_I_15_2, S. 37;
         <!-- Fischer-Lamberg --> faust://bibliography/inventare_2_2, Sp. 120). Dass die von Schmidt
         unter unter derselben Sigle verzeichneten Streifen angesteckt waren
         (faust://bibliography/wa_I_15_2, S. 37), ist an mehreren Nadelstichlöchern
         erkennbar.
         Zettel, 1 beschriebene Seite. – Vs.: Aufdruck. Rs.: Versentwürfe zu ‚Faust II‘, Akt
         2 (eigenhändig, Tinte).</note>
      <repository>gsa</repository>
      <idno type="faustedition">2 II H.2:1</idno>
      <idno type="gsa_1">GSA 25/XVII,7,3:1</idno>
      <idno type="gsa_2">GSA 25/W 1488</idno>
      <idno type="gsa_ident">390884</idno>
      <idno type="wa_faust">2 II H.2</idno>
      <idno type="fischer_lamberg">2 II H.2b</idno>
      <textTranscript uri="390884.xml"/>
      <f:classification>Konzept</f:classification>
      <dimensions>
         <width unit="mm">80</width>
         <height unit="mm">176</height>
      </dimensions>
      <note>Der Mindestwert für die Breite des Streifens beträgt 76 mm.</note>
      <format>none</format>
      <edges>uncut</edges>
      <paperType>Schreibpapier</paperType>
      <paperColour>grünlich</paperColour>
      <watermarkID>none</watermarkID>
      <references>
         <f:reference type="description" uri="faust://bibliography/wa_I_15_2">S. 37</f:reference>
         <reference type="description" uri="faust://bibliography/fischer-lamberg1955">S.
            25f.</reference>
         <reference type="description" uri="faust://bibliography/bohnenkamp1994">S. 468</reference>
         <reference type="text" uri="faust://bibliography/bohnenkamp1994">S. 468</reference>
         <reference type="text" uri="faust://bibliography/schoene2005">Bd. 1, S. 645</reference>
         <reference type="essay" uri="faust://bibliography/fischer-lamberg1955">S. 26</reference>
         <reference type="essay" uri="faust://bibliography/bohnenkamp1994">S. 468</reference>
      </references>
   </metadata>
   <disjunctLeaf>
      <page>
         <metadata>
            <docTranscript uri="0002.xml"/>
         </metadata>
      </page>
      <page>
         <metadata>
            <docTranscript uri="0003.xml"/>
         </metadata>
      </page>
   </disjunctLeaf>
   <f:metadataImport xmlns:ge="http://www.tei-c.org/ns/geneticEditions" xmlns:svg="http://www.w3.org/2000/svg">
      <f:archiveDatabase xml:space="preserve">
      <f:bemerkung>zur Datierung vgl. Bohnenkamp, S.468</f:bemerkung>
      <f:bestandbildner>Goethe, Johann Wolfgang von / Werke</f:bestandbildner>
      <f:bestandnr>25</f:bestandnr>
      <f:blatt>1</f:blatt>
      <f:dabei_vermerk>Notizen egh: "R. 60/ Sh 25/ Lf 50"</f:dabei_vermerk>
      <f:datierung>ab dem 29.9.1827</f:datierung>
      <f:druckort>WA I 15.1, 90-100-, WA I 15.1, 90-176</f:druckort>
      <f:ident>390884</f:ident>
      <f:kurztitel>Faust. Zweiter Theil. Zweiter Act. Hochgewölbtes enges gothisches Zimmer
WA: II H.2; vgl. I 15.2,37
auf Programm des Weimarer Theaters vom 29.9.1827 zu "Der Freischütz" Oper von C. M. v. Weber, Druck, Bruchstück

Vers(e): 6578-6579
Blut das ich ihm ...
Konzept

Faust. Zweiter Theil. Zweiter Act
Paralipomenon 127
Das muß dich nicht verdrießen ...
Konzept
Text der Handschrift zu WA: I 15.2,217</f:kurztitel>
      <f:ordnungsgruppe>Werke</f:ordnungsgruppe>
      <f:schrift>egh</f:schrift>
      <f:signatur>XVII,7,3:1</f:signatur>
      <f:zwueber>Dramatische Werke</f:zwueber>
    </f:archiveDatabase>
      <f:inventoryDatabase>
         <f:field>
            <f:key n="08">Signatur</f:key>
            <f:value>25/XVII,7,3:1*a</f:value>
         </f:field>
         <f:field>
            <f:key n="081">Bestandsbezeichnung</f:key>
            <f:value>Bestand Goethe, Johann Wolfgang von / Werke</f:value>
         </f:field>
         <f:field>
            <f:key n="11">Kurzbezeichnung (WA-Kategorie mit Texterstreckung)</f:key>
            <f:value>Faust II. WA I 15.1, 1-I 15.2, 247</f:value>
         </f:field>
         <f:field>
            <f:key n="11z">Druckstelle in der WA</f:key>
            <f:value>I 15.1,90-100</f:value>
         </f:field>
         <f:field>
            <f:key n="14">vorgefundenes Inzipit</f:key>
            <f:value>Blut das ich ihm</f:value>
         </f:field>
         <f:field>
            <f:key n="30">Schrift</f:key>
            <f:value>egh</f:value>
         </f:field>
         <f:field>
            <f:key n="333">Überlieferungsform</f:key>
            <f:value>Konzept</f:value>
         </f:field>
         <f:field>
            <f:key n="41v">Verszahlen</f:key>
            <f:value>6578-6579</f:value>
         </f:field>
         <f:field>
            <f:key n="xx0">Datensatznr.</f:key>
            <f:value>2495</f:value>
         </f:field>
      </f:inventoryDatabase>
      <f:inventoryDatabase>
         <f:field>
            <f:key n="08">Signatur</f:key>
            <f:value>25/XVII,7,3:1</f:value>
         </f:field>
         <f:field>
            <f:key n="081">Bestandsbezeichnung</f:key>
            <f:value>Bestand Goethe, Johann Wolfgang von / Werke</f:value>
         </f:field>
         <f:field>
            <f:key n="12e">ermittelte Datierung</f:key>
            <f:value>ab dem 29.9.1827</f:value>
         </f:field>
         <f:field>
            <f:key n="12i">Index-Datum</f:key>
            <f:value>18270929 (terminus post quem)</f:value>
         </f:field>
         <f:field>
            <f:key n="20">Handschriftennachweis in WA und SNA</f:key>
            <f:value>I 15.2,37</f:value>
         </f:field>
         <f:field>
            <f:key n="25">Sigle</f:key>
            <f:value>II H.2</f:value>
         </f:field>
         <f:field>
            <f:key n="70">Personen</f:key>
            <f:value>Weber, Karl Maria von</f:value>
         </f:field>
         <f:field>
            <f:key n="80">Blattzahl</f:key>
            <f:value>1</f:value>
         </f:field>
         <f:field>
            <f:key n="90">dabei-Vermerk</f:key>
            <f:value>Notizen egh: "R. 60/ Sh 25/ Lf 50"</f:value>
         </f:field>
         <f:field>
            <f:key n="91">Kommentar</f:key>
            <f:value>zur Datierung vgl. Bohnenkamp, S.468</f:value>
         </f:field>
         <f:field>
            <f:key n="992">Überlieferungszusammenhang</f:key>
            <f:value>auf Programm des Weimarer Theaters vom 29.9.1827 zu "Der Freischütz" Oper von
               K. M. v. Weber, Druck, Bruchstück</f:value>
         </f:field>
         <f:field>
            <f:key n="994">Filmnummer</f:key>
            <f:value>1148</f:value>
         </f:field>
         <f:field>
            <f:key n="xx0">Datensatznr.</f:key>
            <f:value>2813</f:value>
         </f:field>
         <f:paralipomenon>
            <f:field>
               <f:key n="08a">Signatur in der Bohnenkamp-Datei</f:key>
               <f:value>25/XVII,7,3:1*b</f:value>
            </f:field>
            <f:field>
               <f:key n="21">WA-Abtlg. Bd. S.</f:key>
               <f:value>I 15.2,37: H.2</f:value>
            </f:field>
            <f:field>
               <f:key n="26">Bohnenkamp-Sigle</f:key>
               <f:value>II H 2b</f:value>
            </f:field>
            <f:field>
               <f:key n="41b">Bohnenkamp-Seite</f:key>
               <f:value>468</f:value>
            </f:field>
            <f:field>
               <f:key n="41h">Hecker-Nummer</f:key>
               <f:value>172</f:value>
            </f:field>
            <f:field>
               <f:key n="42i">Bohnenkamp-Inzipit</f:key>
               <f:value>Das muß dich nicht verdrießen</f:value>
            </f:field>
            <f:field>
               <f:key n="43">WA-Paralipomenon-Nummer</f:key>
               <f:value>127</f:value>
            </f:field>
            <f:field>
               <f:key n="xx0">Datensatznr.</f:key>
               <f:value>10052</f:value>
            </f:field>
         </f:paralipomenon>
      </f:inventoryDatabase>
      <f:inventoryDatabase>
         <f:field>
            <f:key n="08">Signatur</f:key>
            <f:value>25/XVII,7,3:1*b</f:value>
         </f:field>
         <f:field>
            <f:key n="081">Bestandsbezeichnung</f:key>
            <f:value>Bestand Goethe, Johann Wolfgang von / Werke</f:value>
         </f:field>
         <f:field>
            <f:key n="11">Kurzbezeichnung (WA-Kategorie mit Texterstreckung)</f:key>
            <f:value>Faust II. WA I 15.1, 1-I 15.2, 247</f:value>
         </f:field>
         <f:field>
            <f:key n="11z">Druckstelle in der WA</f:key>
            <f:value>I 15.1,90</f:value>
         </f:field>
         <f:field>
            <f:key n="14">vorgefundenes Inzipit</f:key>
            <f:value>Das muß dich nicht verdrießen</f:value>
         </f:field>
         <f:field>
            <f:key n="30">Schrift</f:key>
            <f:value>egh</f:value>
         </f:field>
         <f:field>
            <f:key n="333">Überlieferungsform</f:key>
            <f:value>Konzept</f:value>
         </f:field>
         <f:field>
            <f:key n="41p">Paralipomenon</f:key>
            <f:value>127</f:value>
         </f:field>
         <f:field>
            <f:key n="41z">Druckstelle: Prosatexte und Dramen ohne Verszählung (Band, Seite, Zeile)
               bzw. Paralipomena</f:key>
            <f:value>I 15.2,217</f:value>
         </f:field>
         <f:field>
            <f:key n="xx0">Datensatznr.</f:key>
            <f:value>3383</f:value>
         </f:field>
      </f:inventoryDatabase>
   </f:metadataImport>
</archivalDocument>