<?xml version="1.0" encoding="UTF-8"?>
<macrogenesis xmlns="http://www.faustedition.net/ns"
    xmlns:xsi="http://www.w3.org/2001/XMLSchema-instance"
    xsi:schemaLocation="http://www.faustedition.net/ns https://faustedition.uni-wuerzburg.de/xml/schema/macrogenesis.xsd">
    
    <relation name="temp-pre">
        <source uri="faust://bibliography/wa_i_15_2">S.134</source>
        <item uri="faust://document/wa/2_IV_H.2"/>
        <item uri="faust://document/wa/2_IV_H.3"/>
    </relation>
    <relation name="temp-pre">
        <source uri="faust://bibliography/wa_i_15_2">S.134</source>
        <item uri="faust://document/wa/2_IV_H.4"/>
        <item uri="faust://document/wa/2_IV_H.3"/>
        <item uri="faust://document/wa/2_IV_H"/>
    </relation>
    <relation name="temp-pre">
        <source uri="faust://bibliography/wa_i_15_2">S.135</source>
        <item uri="faust://document/wa/2_IV_H.5"/>
        <item uri="faust://document/wa/2_IV_H.2"/>
        <item uri="faust://document/wa/2_IV_H"/>
        <item uri="faust://document/wa/C_41"/>
    </relation>
    <relation name="temp-pre">
        <source uri="faust://bibliography/wa_i_15_2">S.135</source>
        <item uri="faust://document/wa/2_IV_H.2"/>
        <item uri="faust://document/wa/2_IV_H"/>
    </relation>
    <relation name="temp-pre">
        <source uri="faust://bibliography/wa_i_15_2">S.135</source>
        <item uri="faust://document/wa/2_IV_H.2"/>
        <item uri="faust://document/wa/2_IV_H.7"/>
        <!-- Woraus geht das hervor? Ich vermute, hier wurden die Einträge zu vor 10210 und vor 10212 vermengt. -GB -->
    </relation>
    <relation name="temp-pre">
        <source uri="faust://bibliography/wa_i_15_2">S.135</source>
        <item uri="faust://document/wa/2_IV_H.7"/>
        <item uri="faust://document/wa/C.1_41"/>
    </relation>
    <relation name="temp-pre">
        <source uri="faust://bibliography/wa_i_15_2">S.135</source>
        <item uri="faust://document/wa/2_IV_H"/>
        <item uri="faust://document/wa/C_41"/>
    </relation>
    <relation name="temp-pre">
        <source uri="faust://bibliography/wa_i_15_2">S.136</source>
        <item uri="faust://document/wa/2_IV_H.7"/>
        <item uri="faust://document/wa/2_IV_H"/>
    </relation>  
    <relation name="temp-pre">
        <source uri="faust://bibliography/wa_i_15_2">S.136</source>
        <item uri="faust://document/wa/2_IV_H.8"/>
        <item uri="faust://document/wa/2_IV_H"/>
    </relation>
    <relation name="temp-pre">
        <source uri="faust://bibliography/wa_i_15_2">S.137</source>
        <item uri="faust://document/wa/2_IV_H.8"/>
        <item uri="faust://document/wa/2_IV_H.9"/>
        <item uri="faust://document/wa/2_IV_H"/>
    </relation> 
    <relation name="temp-pre">
        <source uri="faust://bibliography/wa_i_15_2">S.137</source>
        <item uri="faust://document/wa/2_IV_H.10"/>
        <item uri="faust://document/wa/2_IV_H.11"/>
        <item uri="faust://document/wa/2_IV_H"/>
    </relation> 
    <relation name="temp-pre">
        <source uri="faust://bibliography/wa_i_15_2">S.137</source>
        <item uri="faust://document/wa/2_IV_H.13"/>
        <item uri="faust://document/wa/2_IV_H"/>
    </relation>
    <relation name="temp-pre">
        <source uri="faust://bibliography/wa_i_15_2">S.137</source>
        <item uri="faust://document/wa/2_IV_H.12"/>
        <item uri="faust://document/wa/2_IV_H.13"/>
        <item uri="faust://document/wa/2_IV_H"/>
    </relation>
    <relation name="temp-pre">
        <source uri="faust://bibliography/wa_i_15_2">S.137</source>
        <item uri="faust://document/wa/2_IV_H.12"/>
        <item uri="faust://document/wa/2_IV_H.6"/>
    </relation>
    <relation name="temp-pre">
        <source uri="faust://bibliography/wa_i_15_2">S.138</source>
        <item uri="faust://document/wa/2_IV_H.13"/>
        <item uri="faust://document/wa/2_IV_H.14"/>
    </relation>
    <relation name="temp-pre">
        <source uri="faust://bibliography/wa_i_15_2">S.138</source>
        <item uri="faust://document/wa/2_IV_H.11"/>
        <item uri="faust://document/wa/2_IV_H"/>
        <item uri="faust://document/wa/C_41"/>
    </relation>
    <relation name="temp-pre">
        <source uri="faust://bibliography/wa_i_15_2">S.138</source>
        <item uri="faust://document/wa/2_IV_H.11"/>
        <item uri="faust://document/wa/2_IV_H.15"/>
    </relation>
    <relation name="temp-pre">
        <source uri="faust://bibliography/wa_i_15_2">S.138</source>
        <item uri="faust://document/wa/2_IV_H.14"/>
        <item uri="faust://document/wa/C.1_41"/>
    </relation>
    <relation name="temp-pre">
        <source uri="faust://bibliography/wa_i_15_2">S.138</source>
        <item uri="faust://document/wa/2_IV_H.14"/>
        <item uri="faust://document/wa/2_IV_H.13"/>
        <item uri="faust://document/wa/2_IV_H"/>
    </relation>
    <relation name="temp-pre">
        <source uri="faust://bibliography/wa_i_15_2">S.138</source>
        <item uri="faust://document/wa/2_IV_H.10"/>
        <item uri="faust://document/wa/2_IV_H.13"/>
        <item uri="faust://document/wa/2_IV_H"/>
    </relation>
    <relation name="temp-pre">
        <source uri="faust://bibliography/wa_i_15_2">S.138</source>
        <item uri="faust://document/wa/2_IV_H.15"/>
        <item uri="faust://document/wa/2_IV_H.13"/>
        <item uri="faust://document/wa/2_IV_H"/>
    </relation>
    <relation name="temp-pre">
        <source uri="faust://bibliography/wa_i_15_2">S.139</source>
        <item uri="faust://document/wa/2_IV_H.17"/>
        <item uri="faust://document/wa/2_IV_H.18"/>
        <item uri="faust://document/wa/2_IV_H.13"/>
    </relation>
    <relation name="temp-pre">
        <source uri="faust://bibliography/wa_i_15_2">S.140</source>
        <item uri="faust://document/wa/2_IV_H.13"/>
        <item uri="faust://document/wa/2_IV_H"/>
        <item uri="faust://document/wa/C_41"/>
    </relation>
    <relation name="temp-pre">
        <source uri="faust://bibliography/wa_i_15_2">S. 141</source>
        <item uri="faust://document/wa/2_IV_H.6"/>
        <item uri="faust://document/wa/2_IV_H.20"/>
        <item uri="faust://document/wa/2_IV_H.21"/>
    </relation>
    <relation name="temp-pre">
        <source uri="faust://bibliography/wa_i_15_2">S.141</source>
        <item uri="faust://document/wa/2_IV_H.17"/>
        <item uri="faust://document/wa/2_IV_H.c"/>
    </relation>
    <relation name="temp-pre">
        <source uri="faust://bibliography/wa_i_15_2">S.141</source>
        <item uri="faust://document/wa/2_IV_H.c"/>
        <item uri="faust://document/wa/2_IV_H"/>
    </relation>
    <relation name="temp-pre">
        <source uri="faust://bibliography/wa_i_15_2">S.141</source>
        <item uri="faust://document/wa/2_IV_H.22"/>
        <item uri="faust://document/wa/2_IV_H"/>
    </relation>
    <relation name="temp-pre">
        <source uri="faust://bibliography/wa_i_15_2">S.142</source>
        <item uri="faust://document/wa/2_IV_H.8"/>
        <item uri="faust://document/wa/2_IV_H"/>
    </relation>
    <relation name="temp-pre">
        <source uri="faust://bibliography/wa_i_15_2">S.142</source>
        <item uri="faust://document/wa/2_IV_H.d"/>
        <item uri="faust://document/wa/2_IV_H.8"/>
        <item uri="faust://document/wa/2_IV_H"/>
    </relation>
    <relation name="temp-pre">
        <source uri="faust://bibliography/wa_i_15_2">S.142f</source>
        <item uri="faust://document/wa/2_IV_H.e"/>
        <item uri="faust://document/wa/2_IV_H.8"/>
    </relation>
    <relation name="temp-pre">
        <source uri="faust://bibliography/wa_i_15_2">S.143</source>
        <item uri="faust://document/wa/2_IV_H.d"/>
        <item uri="faust://document/wa/2_IV_H.e"/>
        <item uri="faust://document/wa/2_IV_H.8"/>
        <item uri="faust://document/wa/2_IV_H"/>
    </relation>
    <relation name="temp-pre">
        <source uri="faust://bibliography/wa_i_15_2">S.144</source>
        <item uri="faust://document/wa/2_IV_H.f"/>
        <item uri="faust://document/wa/2_IV_H.20"/>
        <item uri="faust://document/wa/2_IV_H.b"/>
    </relation>
    <relation name="temp-pre">
        <source uri="faust://bibliography/wa_i_15_2">S.144</source>
        <item uri="faust://document/wa/2_IV_H.b"/>
        <item uri="faust://document/wa/2_IV_H"/>
    </relation>
    <relation name="temp-pre">
        <source uri="faust://bibliography/wa_i_15_2">S.144</source>
        <item uri="faust://document/wa/2_IV_H.20"/>
        <item uri="faust://document/wa/2_IV_H"/>
    </relation>
    <relation name="temp-pre">
        <source uri="faust://bibliography/wa_i_15_2">S.144f</source>
        <item uri="faust://document/wa/2_IV_H.b"/>
        <item uri="faust://document/wa/2_IV_H.1"/>
        <!-- vorher umgekehrt; korrigiert GB -->
    </relation>
    <relation name="temp-pre">
        <source uri="faust://bibliography/wa_i_15_2">S.145</source>
        <item uri="faust://document/wa/2_IV_H.g"/>
        <item uri="faust://document/wa/2_IV_H"/>
    </relation>
    <relation name="temp-pre">
        <source uri="faust://bibliography/wa_i_15_2">S.146</source>
        <item uri="faust://document/wa/2_IV_H.h"/>
        <item uri="faust://document/wa/2_IV_H.g"/>
        <item uri="faust://document/wa/C_41"/>
    </relation>
    <relation name="temp-pre">
        <source uri="faust://bibliography/wa_i_15_2">S.146</source>
        <item uri="faust://document/wa/2_IV_H.h"/>
        <item uri="faust://document/wa/2_IV_H"/>
    </relation>
</macrogenesis>
